{"cameraMode":{"drawMode":0,"name":"Shaded","section":"Shading Mode"},"sceneLighting":true,"audioPlay":false,"sceneViewState":{"m_AlwaysRefresh":false,"showFog":true,"showSkybox":true,"showFlares":true,"showImageEffects":true,"showParticleSystems":true,"showVisualEffectGraphs":true,"m_FxEnabled":true},"in2DMode":false,"pivot":{"x":0.9559934139251709,"y":-12.476997375488282,"z":-9.159854888916016},"rotation":{"x":0.015147412195801735,"y":0.8918603658676148,"z":-0.4511398673057556,"w":0.03000400960445404},"size":23.227441787719728,"orthographic":false}